setup.py
emojidb/__init__.py
emojidb/client.py
emojidb/test/__init__.py
emojidb/test/test_client.py
emojidb_python-1.0.1.dist-info/LICENSE
emojidb_python-1.0.1.dist-info/METADATA
emojidb_python-1.0.1.dist-info/WHEEL
emojidb_python-1.0.1.dist-info/top_level.txt
emojidb_python-1.0.1.dist-info/RECORD
