Metadata-Version: 2.1
Name: emojidb-python
Version: 1.0.1
Summary: Simple python wrapper for emojidb.com
Home-page: https://github.com/yedhrab/emojidb-python
Author: Yunus Emre Ak
Author-email: yemreak.com@gmail.com
License: Apache Software License 2.0
Project-URL: Source, https://github.com/yedhrab/emojidb-python/
Project-URL: Changelog, https://github.com/yedhrab/emojidb-python/releases
Project-URL: Issue Tracker, https://github.com/yedhrab/emojidb-python/issues
Keywords: emoji,emojidb,emojidb.com,emojidb-client,emojidb-client-python
Classifier: Development Status :: 5 - Production/Stable
Classifier: Intended Audience :: Developers
Classifier: License :: OSI Approved :: Apache Software License
Classifier: Operating System :: OS Independent
Classifier: Programming Language :: Python :: 3.9
Classifier: Programming Language :: Python :: 3.10
Classifier: Programming Language :: Python :: 3.11
Classifier: Topic :: Utilities
Requires-Python: >=3.9.6
License-File: LICENSE
Requires-Dist: aiohttp (==3.8.4)
Requires-Dist: beautifulsoup4 (==4.12.2)
Provides-Extra: dev
Requires-Dist: black (==23.3.0) ; extra == 'dev'
Requires-Dist: autoflake (==2.0.2) ; extra == 'dev'
Requires-Dist: pytest (==7.3.0) ; extra == 'dev'
Requires-Dist: pytest-asyncio (==0.21.0) ; extra == 'dev'
